<?xml version="1.0" encoding="UTF-8" standalone="no"?>
<root xmlns:xsi="http://www.w3.org/2001/XMLSchema-instance" xsi:noNamespaceSchemaLocation="schema/databaseConnection.xsd">
<databaseconnection identifier="FelixDB">
<name>FelixDB</name>
<description/>
<physicalname>felix\db\FelixDB.db</physicalname>
<logicalname/>
<aliases/>
<group/>
<host>127.0.0.1</host>
<service>9000</service>
<userID/>
<password/>
<connectionparameters/>
<SQLIdentifier>-46cd54d4:164acd06410:-7fdd</SQLIdentifier>
<autoStartServer>true</autoStartServer>
<serverParameters>-db felix\FelixDB\FelixDB.db -S 9000   </serverParameters>
<autoShutdownServer>false</autoShutdownServer>
<OEVersion>11.6</OEVersion>
<SQLAlias>
<autoLogon>true</autoLogon>
<connectAtStartup>false</connectAtStartup>
<driverIdentifier>-27</driverIdentifier>
<SQLAliasIdentifier>-46cd54d4:164acd06410:-7fdd</SQLAliasIdentifier>
<SQLAliasName>FelixDB</SQLAliasName>
<SQLAliasPassword/>
<url>jdbc:datadirect:openedge://localhost:9000;databaseName=FelixDB.db</url>
<useDriverProperties>false</useDriverProperties>
<userName>Studentas</userName>
</SQLAlias>
</databaseconnection>
</root>
